{"name": "Local Comercial en Renta | Av. Lincoln, Monterrey, N.L.", "description": "Descripci\u00f3n Local comercial en renta con excelente exposici\u00f3n sobre Avenida Lincoln, ubicado en una zona de alto flujo vehicular y peatonal, frente a importantes puntos de referencia como el IMSS 34 Cardiolog\u00eda y a contra esquina de Walmart.\n\nDentro de la misma plaza se encuentra una instituci\u00f3n educativa con aproximadamente 900 alumnos, lo que genera afluencia constante y potencial para diversos giros comerciales.\n\nSuperficie: 110 m\u00b2\n1 ba\u00f1o\n$21,000 MXN mensuales\n\nIdeal para comercio, servicios, consultorios o alimentos (sujeto a reglamento de la plaza)\n\nPrecio sujeto a cambio sin previo aviso. EasyBroker ID: EB-WG8411", "price": null, "location": null, "url": "https://www.lamudi.com.mx/detalle/41032-73-ae80db19e1a0-dad5-19ed398-8794-7720", "images": ["https://multimedia.lamudi.com/lamudi/common/images/lamudi.svg", "https://multimedia.lamudi.com/lamudi/common/images/icon-medal_m_white.svg", "https://multimedia.lamudi.com/lamudi/common/images/icon-menu_m_white.svg", "https://images.proppit.com/publisher/0ec056a3-3a32-409a-957f-db5e6eb7c8c7/logo.jpeg", "https://multimedia.lamudi.com/lamudi/common/images/icon-gallery-white.svg", "https://multimedia.lamudi.com/front/0b9dd7e5/adform/assets/images/form/youtube-button.svg", "https://multimedia.lamudi.com/lamudi/common/images/map_bg.png", "https://multimedia.lamudi.com/lamudi/common/images/lamudi-positive.svg", "https://multimedia.lamudi.com/lamudi/common/images/facebook.svg", "https://multimedia.lamudi.com/lamudi/common/images/rss.svg", "https://multimedia.lamudi.com/lamudi/common/images/lc.svg"]}