{"name": "Las Brisas", "description": "Descripci\u00f3n Excelente local ubicado en una de las principales avenidas de Monterrey sobre L\u00e1zaro C\u00e1rdenas (Las Torres), mide 86.40 m2, ideal para negocios de comida, belleza, accesorios, entre otros giros m\u00e1s, se paga el 7% de mantenimiento, est\u00e1 cerca de farmacias, consultorios, centros comerciales, tiendas de conveniencia, etc. No esperes m\u00e1s, este local es para ti, agenda tu cita ahora mismo. Id Gvia: 119735. EasyBroker ID: EB-VC5004", "price": "$ 50,112 MXN /mes", "location": "Brisas Diamante, Monterrey, Nuevo Le\u00f3n", "url": "https://www.lamudi.com.mx/detalle/41032-73-54b2c231e337-5f19-19be3bb-a2ea-78e3", "images": ["https://multimedia.lamudi.com/lamudi/common/images/lamudi.svg", "https://multimedia.lamudi.com/lamudi/common/images/icon-medal_m_white.svg", "https://multimedia.lamudi.com/lamudi/common/images/icon-menu_m_white.svg", "https://images.proppit.com/publisher/348ccb91-b4cf-47c7-ae09-8f93b7dac152/logo.jpeg", "https://multimedia.lamudi.com/lamudi/common/images/icon-gallery-white.svg", "https://multimedia.lamudi.com/front/0b9dd7e5/adform/assets/images/form/youtube-button.svg", "https://multimedia.lamudi.com/lamudi/common/images/map_bg.png", "https://multimedia.lamudi.com/lamudi/common/images/lamudi-positive.svg", "https://multimedia.lamudi.com/lamudi/common/images/facebook.svg", "https://multimedia.lamudi.com/lamudi/common/images/rss.svg", "https://multimedia.lamudi.com/lamudi/common/images/lc.svg"]}